ppilot/__init__.py
ppilot/cpu.py
ppilot/disk.py
ppilot/serve.py
ppilot-0.1.0.dev2.dist-info/LICENSE
ppilot-0.1.0.dev2.dist-info/METADATA
ppilot-0.1.0.dev2.dist-info/WHEEL
ppilot-0.1.0.dev2.dist-info/entry_points.txt
ppilot-0.1.0.dev2.dist-info/top_level.txt
ppilot-0.1.0.dev2.dist-info/RECORD
