Metadata-Version: 2.1
Name: ppilot
Version: 0.1.0.dev2
Summary: An easy-to-use local plugin integration for Agentic LLM Apps.
Author-email: riven2333 <2796839179@qq.com>, blueyo0 <small_dark@sina.com>
License: Apache License
Project-URL: Homepage, https://github.com/riven2333/PrivacyPilot
Requires-Python: >=3.9
License-File: LICENSE
Requires-Dist: fastapi >=0.100.0
Requires-Dist: psutil >=5.8.0
